fdprof/__init__.py
fdprof/_version.py
fdprof/analysis.py
fdprof/core.py
fdprof/demo.py
fdprof/events.py
fdprof/monitoring.py
fdprof/plotting.py
fdprof-0.1.3.dist-info/METADATA
fdprof-0.1.3.dist-info/WHEEL
fdprof-0.1.3.dist-info/entry_points.txt
fdprof-0.1.3.dist-info/RECORD
