Metadata-Version: 2.4
Name: fdprof
Version: 0.1.3
Summary: File descriptor profiler that monitors FD usage and captures timestamped events
Project-URL: Homepage, https://github.com/ianhi/fdprof
Project-URL: Repository, https://github.com/ianhi/fdprof
Project-URL: Issues, https://github.com/ianhi/fdprof/issues
Project-URL: Documentation, https://github.com/ianhi/fdprof#readme
Author-email: Ian Hunt-Isaak <ianhuntisaak@gmail.com>
License-Expression: MIT
Classifier: Development Status :: 4 - Beta
Classifier: Environment :: Console
Classifier: Intended Audience :: Developers
Classifier: License :: OSI Approved :: MIT License
Classifier: Operating System :: MacOS
Classifier: Operating System :: Microsoft :: Windows
Classifier: Operating System :: POSIX
Classifier: Operating System :: Unix
Classifier: Programming Language :: Python :: 3
Classifier: Programming Language :: Python :: 3.11
Classifier: Programming Language :: Python :: 3.12
Classifier: Topic :: Software Development :: Debuggers
Classifier: Topic :: System :: Monitoring
Classifier: Topic :: Utilities
Requires-Python: >=3.11
Requires-Dist: matplotlib>=3.5.0
Requires-Dist: numpy>=1.20.0
Requires-Dist: psutil>=5.8.0
Provides-Extra: dev
Requires-Dist: pre-commit>=3.0.0; extra == 'dev'
Requires-Dist: pytest-cov>=3.0; extra == 'dev'
Requires-Dist: pytest-timeout>=2.0; extra == 'dev'
Requires-Dist: pytest>=6.0; extra == 'dev'
Requires-Dist: ruff>=0.1.0; extra == 'dev'
Requires-Dist: twine>=4.0.0; extra == 'dev'
Provides-Extra: test
Requires-Dist: pytest-cov>=3.0; extra == 'test'
Requires-Dist: pytest-timeout>=2.0; extra == 'test'
Requires-Dist: pytest>=6.0; extra == 'test'
